mcp_server_milvus/README.md
mcp_server_milvus/__init__.py
mcp_server_milvus/server.py
mcp_server_milvus/server.py.bak
iflow_mcp_stephen37_mcp_server_milvus-0.1.0.dist-info/METADATA
iflow_mcp_stephen37_mcp_server_milvus-0.1.0.dist-info/WHEEL
iflow_mcp_stephen37_mcp_server_milvus-0.1.0.dist-info/entry_points.txt
iflow_mcp_stephen37_mcp_server_milvus-0.1.0.dist-info/RECORD
