Metadata-Version: 2.4
Name: iflow-mcp_stephen37_mcp-server-milvus
Version: 0.1.0
Summary: MCP server for Milvus
Requires-Python: >=3.10
Requires-Dist: click>=8.0.0
Requires-Dist: mcp[cli]>=1.1.2
Requires-Dist: pymilvus>=2.5.1
